dvc_objects/__init__.py
dvc_objects/compat.py
dvc_objects/db.py
dvc_objects/errors.py
dvc_objects/executors.py
dvc_objects/obj.py
dvc_objects/py.typed
dvc_objects/transfer.py
dvc_objects/fs/__init__.py
dvc_objects/fs/base.py
dvc_objects/fs/callbacks.py
dvc_objects/fs/errors.py
dvc_objects/fs/generic.py
dvc_objects/fs/local.py
dvc_objects/fs/memory.py
dvc_objects/fs/scheme.py
dvc_objects/fs/system.py
dvc_objects/fs/utils.py
dvc_objects-5.0.0.dist-info/LICENSE
dvc_objects-5.0.0.dist-info/METADATA
dvc_objects-5.0.0.dist-info/WHEEL
dvc_objects-5.0.0.dist-info/top_level.txt
dvc_objects-5.0.0.dist-info/RECORD
