Metadata-Version: 2.1
Name: dvc-objects
Version: 5.0.0
Summary: dvc objects - filesystem and object-db level abstractions to use in dvc and dvc-data
Author-email: Iterative <support@dvc.org>
License: Apache-2.0
Project-URL: Issues, https://github.com/iterative/dvc-objects/issues
Project-URL: Source, https://github.com/iterative/dvc-objects
Classifier: Programming Language :: Python :: 3
Classifier: Programming Language :: Python :: 3.8
Classifier: Programming Language :: Python :: 3.9
Classifier: Programming Language :: Python :: 3.10
Classifier: Programming Language :: Python :: 3.11
Classifier: Programming Language :: Python :: 3.12
Classifier: Development Status :: 4 - Beta
Requires-Python: >=3.8
License-File: LICENSE
Requires-Dist: fsspec >=2024.2.0
Requires-Dist: funcy >=1.14 ; python_version < "3.12"
Provides-Extra: dev
Requires-Dist: dvc-objects[tests] ; extra == 'dev'
Requires-Dist: mypy ==1.8.0 ; extra == 'dev'
Provides-Extra: tests
Requires-Dist: pytest <8,>=7 ; extra == 'tests'
Requires-Dist: pytest-sugar ; extra == 'tests'
Requires-Dist: pytest-cov >=4.1.0 ; extra == 'tests'
Requires-Dist: pytest-mock ; extra == 'tests'
Requires-Dist: pytest-benchmark ; extra == 'tests'
Requires-Dist: pytest-asyncio <1,>=0.23.2 ; extra == 'tests'
Requires-Dist: reflink ; extra == 'tests'
